.gitattributes
.gitignore
LICENSE
README.md
pyproject.toml
setup.py
src/classeviva/__init__.py
src/classeviva/__main__.py
src/classeviva/main.py
src/classevivaAPI.egg-info/PKG-INFO
src/classevivaAPI.egg-info/SOURCES.txt
src/classevivaAPI.egg-info/dependency_links.txt
src/classevivaAPI.egg-info/top_level.txt
src/classeviva/exceptions/__init__.py
src/classeviva/exceptions/exceptions.py
src/classeviva/paths/__init__.py
src/classeviva/paths/paths.py
src/classeviva/variables/__init__.py
src/classeviva/variables/variables.py