Metadata-Version: 2.1
Name: classevivaAPI
Version: 0.2.1.post0
Summary: Classeviva Python API
Home-page: https://github.com/Lioydiano/Classeviva
Author: FLAK-ZOSO
Author-email: mattia.marchese.2006@gmail.com
License: UNKNOWN
Download-URL: https://github.com/Lioydiano/Classeviva/archive/refs/tags/v0.2.1.post0.tar.gz
Keywords: classeviva,school,api
Platform: UNKNOWN
Classifier: Programming Language :: Python :: 3
Classifier: Programming Language :: Python :: 3.10
Classifier: Programming Language :: Python :: Implementation :: CPython
Classifier: Development Status :: 2 - Pre-Alpha
Classifier: License :: OSI Approved :: MIT License
Classifier: Operating System :: OS Independent
Classifier: Intended Audience :: Developers
Classifier: Natural Language :: Italian
Classifier: Natural Language :: English
Classifier: Typing :: Typed
Requires: selenium
Requires-Python: >=3.10
License-File: LICENSE
